gPCS/__init__.py
gPCS/gPCS.py
gPCS/data/TS_map_4FGL.npz
gPCS/data/TS_map_fermi.npz
gPCS/data/TS_star_alpha_0.01.npz
gPCS/data/TS_star_alpha_0.01_4FGL.npz
gPCS/data/TS_star_alpha_0.05.npz
gPCS/data/TS_star_alpha_0.05_4FGL.npz
gPCS/data/TS_star_alpha_0.1.npz
gPCS/data/TS_star_alpha_0.1_4FGL.npz
gPCS/data/fits/README.md
gPCS/data/fits/gll_psc_v30.fit
gpcs-1.0.3.dist-info/METADATA
gpcs-1.0.3.dist-info/WHEEL
gpcs-1.0.3.dist-info/licenses/LICENSE
gpcs-1.0.3.dist-info/RECORD
