Metadata-Version: 2.1
Name: gPCS
Version: 1.0.3
Summary: Code for the paper Deepening gamma-ray point-source catalogues with sub-threshold information
Project-URL: Homepage, https://github.com/aurelio-amerio/gPCS
Project-URL: Bug Tracker, https://github.com/aurelio-amerio/gPCS/issues
Author: Francesca Calore, Pasquale Serpico, Bryan Zaldìvar
Author-email: Aurelio Amerio <aurelio.amerio@ific.uv.es>
License: Copyright (c) 2023 A.Amerio, F.Calore, P.Serpico, B.Zaldìvar
License-File: LICENSE
Classifier: Programming Language :: Python :: 3
Requires-Python: >=3.7
Requires-Dist: astropy
Requires-Dist: healpy
Requires-Dist: numba
Requires-Dist: numpy
